{
  "keyPath": "root->United_States->Midwest->West_North_Central->Nebraska->NE_Corner_of_Nebraska->Dixon_County",
  "nodes": [
    {
      "name": "68710"
    },
    {
      "name": "68732"
    },
    {
      "name": "68770"
    },
    {
      "name": "68784"
    },
    {
      "name": "68785"
    },
    {
      "name": "Dropped_Out"
    },
    {
      "name": "Checkout_Step_1"
    },
    {
      "name": "Checkout_Step_2"
    },
    {
      "name": "Completed_Purchase"
    }
  ],
  "countLinks": [
    {
      "source": 0,
      "target": 5,
      "value": 0,
      "region": "68710"
    },
    {
      "source": 0,
      "target": 6,
      "value": 1,
      "region": "68710"
    },
    {
      "source": 6,
      "target": 5,
      "value": 0,
      "region": "68710"
    },
    {
      "source": 6,
      "target": 7,
      "value": 1,
      "region": "68710"
    },
    {
      "source": 7,
      "target": 5,
      "value": 0,
      "region": "68710"
    },
    {
      "source": 7,
      "target": 8,
      "value": 1,
      "region": "68710"
    },
    {
      "source": 3,
      "target": 5,
      "value": 0,
      "region": "68784"
    },
    {
      "source": 3,
      "target": 6,
      "value": 1,
      "region": "68784"
    },
    {
      "source": 6,
      "target": 5,
      "value": 0,
      "region": "68784"
    },
    {
      "source": 6,
      "target": 7,
      "value": 1,
      "region": "68784"
    },
    {
      "source": 7,
      "target": 5,
      "value": 0,
      "region": "68784"
    },
    {
      "source": 7,
      "target": 8,
      "value": 1,
      "region": "68784"
    },
    {
      "source": 4,
      "target": 5,
      "value": 0,
      "region": "68785"
    },
    {
      "source": 4,
      "target": 6,
      "value": 1,
      "region": "68785"
    },
    {
      "source": 6,
      "target": 5,
      "value": 0,
      "region": "68785"
    },
    {
      "source": 6,
      "target": 7,
      "value": 1,
      "region": "68785"
    },
    {
      "source": 7,
      "target": 5,
      "value": 0,
      "region": "68785"
    },
    {
      "source": 7,
      "target": 8,
      "value": 1,
      "region": "68785"
    },
    {
      "source": 1,
      "target": 5,
      "value": 0,
      "region": "68732"
    },
    {
      "source": 1,
      "target": 6,
      "value": 1,
      "region": "68732"
    },
    {
      "source": 6,
      "target": 5,
      "value": 1,
      "region": "68732"
    },
    {
      "source": 6,
      "target": 7,
      "value": 0,
      "region": "68732"
    },
    {
      "source": 7,
      "target": 5,
      "value": 0,
      "region": "68732"
    },
    {
      "source": 7,
      "target": 8,
      "value": 0,
      "region": "68732"
    },
    {
      "source": 2,
      "target": 5,
      "value": 0,
      "region": "68770"
    },
    {
      "source": 2,
      "target": 6,
      "value": 1,
      "region": "68770"
    },
    {
      "source": 6,
      "target": 5,
      "value": 0,
      "region": "68770"
    },
    {
      "source": 6,
      "target": 7,
      "value": 1,
      "region": "68770"
    },
    {
      "source": 7,
      "target": 5,
      "value": 1,
      "region": "68770"
    },
    {
      "source": 7,
      "target": 8,
      "value": 0,
      "region": "68770"
    }
  ],
  "priceLinks": []
}