{
  "keyPath": "root->United_States->South->West_South_Central->Oklahoma->SE_Corner_of_Oklahoma->Jefferson_County",
  "nodes": [
    {
      "name": "73456"
    },
    {
      "name": "73520"
    },
    {
      "name": "73548"
    },
    {
      "name": "73565"
    },
    {
      "name": "73569"
    },
    {
      "name": "73573"
    },
    {
      "name": "Dropped_Out"
    },
    {
      "name": "Checkout_Step_1"
    },
    {
      "name": "Checkout_Step_2"
    },
    {
      "name": "Completed_Purchase"
    }
  ],
  "countLinks": [
    {
      "source": 0,
      "target": 6,
      "value": 0,
      "region": "73456"
    },
    {
      "source": 0,
      "target": 7,
      "value": 1,
      "region": "73456"
    },
    {
      "source": 7,
      "target": 6,
      "value": 0,
      "region": "73456"
    },
    {
      "source": 7,
      "target": 8,
      "value": 1,
      "region": "73456"
    },
    {
      "source": 8,
      "target": 6,
      "value": 0,
      "region": "73456"
    },
    {
      "source": 8,
      "target": 9,
      "value": 1,
      "region": "73456"
    },
    {
      "source": 2,
      "target": 6,
      "value": 0,
      "region": "73548"
    },
    {
      "source": 2,
      "target": 7,
      "value": 1,
      "region": "73548"
    },
    {
      "source": 7,
      "target": 6,
      "value": 0,
      "region": "73548"
    },
    {
      "source": 7,
      "target": 8,
      "value": 1,
      "region": "73548"
    },
    {
      "source": 8,
      "target": 6,
      "value": 0,
      "region": "73548"
    },
    {
      "source": 8,
      "target": 9,
      "value": 1,
      "region": "73548"
    },
    {
      "source": 4,
      "target": 6,
      "value": 1,
      "region": "73569"
    },
    {
      "source": 4,
      "target": 7,
      "value": 0,
      "region": "73569"
    },
    {
      "source": 7,
      "target": 6,
      "value": 0,
      "region": "73569"
    },
    {
      "source": 7,
      "target": 8,
      "value": 0,
      "region": "73569"
    },
    {
      "source": 8,
      "target": 6,
      "value": 0,
      "region": "73569"
    },
    {
      "source": 8,
      "target": 9,
      "value": 0,
      "region": "73569"
    },
    {
      "source": 5,
      "target": 6,
      "value": 0,
      "region": "73573"
    },
    {
      "source": 5,
      "target": 7,
      "value": 1,
      "region": "73573"
    },
    {
      "source": 7,
      "target": 6,
      "value": 0,
      "region": "73573"
    },
    {
      "source": 7,
      "target": 8,
      "value": 1,
      "region": "73573"
    },
    {
      "source": 8,
      "target": 6,
      "value": 0,
      "region": "73573"
    },
    {
      "source": 8,
      "target": 9,
      "value": 1,
      "region": "73573"
    },
    {
      "source": 1,
      "target": 6,
      "value": 1,
      "region": "73520"
    },
    {
      "source": 1,
      "target": 7,
      "value": 0,
      "region": "73520"
    },
    {
      "source": 7,
      "target": 6,
      "value": 0,
      "region": "73520"
    },
    {
      "source": 7,
      "target": 8,
      "value": 0,
      "region": "73520"
    },
    {
      "source": 8,
      "target": 6,
      "value": 0,
      "region": "73520"
    },
    {
      "source": 8,
      "target": 9,
      "value": 0,
      "region": "73520"
    },
    {
      "source": 3,
      "target": 6,
      "value": 1,
      "region": "73565"
    },
    {
      "source": 3,
      "target": 7,
      "value": 0,
      "region": "73565"
    },
    {
      "source": 7,
      "target": 6,
      "value": 0,
      "region": "73565"
    },
    {
      "source": 7,
      "target": 8,
      "value": 0,
      "region": "73565"
    },
    {
      "source": 8,
      "target": 6,
      "value": 0,
      "region": "73565"
    },
    {
      "source": 8,
      "target": 9,
      "value": 0,
      "region": "73565"
    }
  ],
  "priceLinks": []
}