{
  "keyPath": "root->United_States->Midwest->East_North_Central->Illinois->NW_Corner_of_Illinois->Mason_County",
  "nodes": [
    {
      "name": "61532"
    },
    {
      "name": "62633"
    },
    {
      "name": "62644"
    },
    {
      "name": "62655"
    },
    {
      "name": "62682"
    },
    {
      "name": "Dropped_Out"
    },
    {
      "name": "Checkout_Step_1"
    },
    {
      "name": "Checkout_Step_2"
    },
    {
      "name": "Completed_Purchase"
    }
  ],
  "countLinks": [
    {
      "source": 1,
      "target": 5,
      "value": 1,
      "region": "62633"
    },
    {
      "source": 1,
      "target": 6,
      "value": 0,
      "region": "62633"
    },
    {
      "source": 6,
      "target": 5,
      "value": 0,
      "region": "62633"
    },
    {
      "source": 6,
      "target": 7,
      "value": 0,
      "region": "62633"
    },
    {
      "source": 7,
      "target": 5,
      "value": 0,
      "region": "62633"
    },
    {
      "source": 7,
      "target": 8,
      "value": 0,
      "region": "62633"
    },
    {
      "source": 2,
      "target": 5,
      "value": 0,
      "region": "62644"
    },
    {
      "source": 2,
      "target": 6,
      "value": 1,
      "region": "62644"
    },
    {
      "source": 6,
      "target": 5,
      "value": 0,
      "region": "62644"
    },
    {
      "source": 6,
      "target": 7,
      "value": 1,
      "region": "62644"
    },
    {
      "source": 7,
      "target": 5,
      "value": 0,
      "region": "62644"
    },
    {
      "source": 7,
      "target": 8,
      "value": 1,
      "region": "62644"
    },
    {
      "source": 4,
      "target": 5,
      "value": 0,
      "region": "62682"
    },
    {
      "source": 4,
      "target": 6,
      "value": 1,
      "region": "62682"
    },
    {
      "source": 6,
      "target": 5,
      "value": 0,
      "region": "62682"
    },
    {
      "source": 6,
      "target": 7,
      "value": 1,
      "region": "62682"
    },
    {
      "source": 7,
      "target": 5,
      "value": 0,
      "region": "62682"
    },
    {
      "source": 7,
      "target": 8,
      "value": 1,
      "region": "62682"
    },
    {
      "source": 0,
      "target": 5,
      "value": 0,
      "region": "61532"
    },
    {
      "source": 0,
      "target": 6,
      "value": 1,
      "region": "61532"
    },
    {
      "source": 6,
      "target": 5,
      "value": 0,
      "region": "61532"
    },
    {
      "source": 6,
      "target": 7,
      "value": 1,
      "region": "61532"
    },
    {
      "source": 7,
      "target": 5,
      "value": 0,
      "region": "61532"
    },
    {
      "source": 7,
      "target": 8,
      "value": 1,
      "region": "61532"
    },
    {
      "source": 3,
      "target": 5,
      "value": 0,
      "region": "62655"
    },
    {
      "source": 3,
      "target": 6,
      "value": 1,
      "region": "62655"
    },
    {
      "source": 6,
      "target": 5,
      "value": 0,
      "region": "62655"
    },
    {
      "source": 6,
      "target": 7,
      "value": 1,
      "region": "62655"
    },
    {
      "source": 7,
      "target": 5,
      "value": 0,
      "region": "62655"
    },
    {
      "source": 7,
      "target": 8,
      "value": 1,
      "region": "62655"
    }
  ],
  "priceLinks": []
}